hpc_suite/__init__.py
hpc_suite/__version__.py
hpc_suite/action.py
hpc_suite/cli.py
hpc_suite/generate_job.py
hpc_suite/store.py
hpc_suite-1.12.2.dist-info/licenses/LICENSE
hpc_suite-1.12.2.dist-info/METADATA
hpc_suite-1.12.2.dist-info/WHEEL
hpc_suite-1.12.2.dist-info/entry_points.txt
hpc_suite-1.12.2.dist-info/top_level.txt
hpc_suite-1.12.2.dist-info/RECORD
