Metadata-Version: 2.4
Name: hpc-suite
Version: 1.12.2
Summary: A package for working with data on HPC platforms
Home-page: https://gitlab.com/chilton-group/hpc_suite
Author: Chilton Group
Author-email: nicholas.chilton@manchester.ac.uk
Project-URL: Bug Tracker, https://gitlab.com/chilton-group/hpc_suite/-/issues
Project-URL: Documentation, https://chilton-group.gitlab.io/hpc_suite
Classifier: Programming Language :: Python :: 3
Classifier: License :: OSI Approved :: GNU General Public License v3 (GPLv3)
Classifier: Operating System :: OS Independent
Requires-Python: >=3.6
License-File: LICENSE
Requires-Dist: numpy
Requires-Dist: h5py
Dynamic: author
Dynamic: author-email
Dynamic: classifier
Dynamic: description
Dynamic: description-content-type
Dynamic: home-page
Dynamic: license-file
Dynamic: project-url
Dynamic: requires-dist
Dynamic: requires-python
Dynamic: summary
